interpreter/.DS_Store
interpreter/__init__.py
interpreter/config.yaml
interpreter/core/.DS_Store
interpreter/core/__init__.py
interpreter/core/code_interpreters/__init__.py
interpreter/core/code_interpreters/base_code_interpreter.py
interpreter/core/code_interpreters/create_code_interpreter.py
interpreter/core/code_interpreters/language_map.py
interpreter/core/code_interpreters/languages/__init__.py
interpreter/core/code_interpreters/languages/applescript.py
interpreter/core/code_interpreters/languages/html.py
interpreter/core/code_interpreters/languages/javascript.py
interpreter/core/code_interpreters/languages/powershell.py
interpreter/core/code_interpreters/languages/python.py
interpreter/core/code_interpreters/languages/python_vision.py
interpreter/core/code_interpreters/languages/r.py
interpreter/core/code_interpreters/languages/shell.py
interpreter/core/code_interpreters/subprocess_code_interpreter.py
interpreter/core/core.py
interpreter/core/generate_system_message.py
interpreter/core/llm/ARCHIVE_setup_local_text_llm.py
interpreter/core/llm/__init__.py
interpreter/core/llm/convert_to_coding_llm.py
interpreter/core/llm/setup_llm.py
interpreter/core/llm/setup_openai_coding_llm.py
interpreter/core/llm/setup_text_llm.py
interpreter/core/rag/ARCHIVE_local_get_relevant_procedures_string.py
interpreter/core/rag/__init__.py
interpreter/core/rag/get_relevant_procedures_string.py
interpreter/core/respond.py
interpreter/core/utils/ARCHIVE_embed.py
interpreter/core/utils/ARCHIVE_vector_search.py
interpreter/core/utils/__init__.py
interpreter/core/utils/convert_to_openai_messages.py
interpreter/core/utils/get_user_info_string.py
interpreter/core/utils/html_to_base64.py
interpreter/core/utils/merge_deltas.py
interpreter/core/utils/parse_partial_json.py
interpreter/core/utils/scan_code.py
interpreter/core/utils/system_debug_info.py
interpreter/core/utils/temporary_file.py
interpreter/core/utils/truncate_output.py
interpreter/terminal_interface/.DS_Store
robotgpt_interpreter-0.0.17.dist-info/METADATA
robotgpt_interpreter-0.0.17.dist-info/WHEEL
robotgpt_interpreter-0.0.17.dist-info/entry_points.txt
robotgpt_interpreter-0.0.17.dist-info/RECORD
